domain/__init__.py
domain/__main__.py
domain/entry_points/__init__.py
domain/entry_points/run_dmt.py
domain/management/__init__.py
domain/management/tools.py
dmt-1.5.8.dist-info/LICENSE
dmt-1.5.8.dist-info/METADATA
dmt-1.5.8.dist-info/WHEEL
dmt-1.5.8.dist-info/entry_points.txt
dmt-1.5.8.dist-info/top_level.txt
dmt-1.5.8.dist-info/RECORD
