Metadata-Version: 2.1
Name: dmt
Version: 1.5.8
Summary: Manage domains like packages.
Home-page: https://gitlab.com/waser-technologies/technologies/dmt
Author: Danny Waser
License: LICENSE
Project-URL: Documentation, https://gitlab.com/waser-technologies/technologies/dmt/blob/main/README.md
Project-URL: Code, https://gitlab.com/waser-technologies/technologies/dmt
Project-URL: Issue tracker, https://gitlab.com/waser-technologies/technologies/dmt/issues
Classifier: Programming Language :: Python :: 3
Classifier: Programming Language :: Python :: 3.8
Classifier: Programming Language :: Python :: 3.9
Classifier: Programming Language :: Python :: 3.10
Classifier: License :: OSI Approved :: MIT License
Classifier: Operating System :: OS Independent
Classifier: Natural Language :: English
Classifier: Natural Language :: French
Requires-Python: >=3.8,<3.12
License-File: LICENSE
Requires-Dist: prompt-toolkit (<3.1.0,>=2.0.0)
Requires-Dist: tqdm
Requires-Dist: halo
Requires-Dist: rich
Requires-Dist: pyyaml
Requires-Dist: requests
Requires-Dist: transformers
